ebbinghaus/__init__.py
ebbinghaus/database.py
ebbinghaus/exceptions.py
ebbinghaus-0.2.0.dist-info/LICENSE
ebbinghaus-0.2.0.dist-info/METADATA
ebbinghaus-0.2.0.dist-info/WHEEL
ebbinghaus-0.2.0.dist-info/top_level.txt
ebbinghaus-0.2.0.dist-info/RECORD
