Metadata-Version: 2.1
Name: ebbinghaus
Version: 0.2.0
Summary: Ebbinghaus remembering curve.
Home-page: https://github.com/pypa/sampleproject
Author: wolfpan
Author-email: haoyupan@aliyun.com
License: UNKNOWN
Platform: UNKNOWN
Classifier: Programming Language :: Python :: 3
Classifier: Operating System :: OS Independent
